{"0": ["6079_bother", "5875_escape", "5870_poke"], "1": ["5948_flirt with", "6004_herd", "5814_talk"], "2": ["6004_herd", "1145_leave", "6012_kiss"], "3": ["4397_hug", "6017_encircle", "1012_push"], "4": ["5948_flirt with", "6035_capture", "6079_bother"], "5": ["5809_pull", "5948_flirt with", "6079_bother"], "6": ["6016_scratch", "5948_flirt with", "5849_approach"], "7": ["5787_accompany", "1012_push", "5814_talk"], "8": ["6005_throw", "5816_ignore", "5870_poke"], "9": ["4397_hug", "5987_creep up on", "4408_lead"], "10": ["5991_examine", "6016_scratch", "5986_fight"], "11": ["6035_capture", "5816_ignore", "5878_follow"], "12": ["6079_bother", "5991_examine", "5814_talk"], "13": ["5843_huddle with", "1012_push", "5816_ignore"], "14": ["4397_hug", "5991_examine", "6016_scratch"], "15": ["6016_scratch", "5875_escape", "6004_herd"], "16": ["1012_push", "6004_herd", "5991_examine"], "17": ["5814_talk", "5987_creep up on", "5948_flirt with"], "18": ["6016_scratch", "5902_hit", "5878_follow"], "19": ["5991_examine", "5987_creep up on", "5870_poke"], "20": ["5849_approach", "5787_accompany", "6005_throw"], "21": ["5814_talk", "5902_hit", "5787_accompany"], "22": ["5902_hit", "6005_throw", "6035_capture"], "23": ["5849_approach", "1145_leave", "6005_throw"], "24": ["6004_herd", "5849_approach", "6012_kiss"], "25": ["5816_ignore", "6017_encircle", "1012_push"], "26": ["6005_throw", "5914_tickle", "5878_follow"], "27": ["5843_huddle with", "5849_approach", "5986_fight"], "28": ["4397_hug", "5809_pull", "5787_accompany"], "29": ["6034_avoid", "5809_pull", "5814_talk"], "30": ["6034_avoid", "5914_tickle", "5991_examine"], "31": ["6016_scratch", "5787_accompany", "6012_kiss"], "32": ["6012_kiss", "6004_herd", "5787_accompany"], "33": ["5902_hit", "1012_push", "6034_avoid"], "34": ["5878_follow", "5814_talk", "4408_lead"], "35": ["6005_throw", "5878_follow", "5849_approach"], "36": ["6004_herd", "5987_creep up on", "5870_poke"], "37": ["5878_follow", "6035_capture", "1145_leave"], "38": ["1145_leave", "6012_kiss", "6016_scratch"], "39": ["5878_follow", "1145_leave", "4408_lead"], "40": ["6017_encircle", "5914_tickle", "6004_herd"], "41": ["1145_leave", "5809_pull", "6016_scratch"], "42": ["6016_scratch", "5843_huddle with", "5914_tickle"], "43": ["5870_poke", "5875_escape", "5843_huddle with"], "44": ["6035_capture", "5948_flirt with", "6012_kiss"]}