{"0": ["1145_leave", "5787_accompany", "5809_pull"], "1": ["5948_flirt with", "4408_lead", "6012_kiss"], "2": ["5849_approach", "5991_examine", "5878_follow"], "3": ["5991_examine", "5843_huddle with", "5986_fight"], "4": ["5991_examine", "6035_capture", "6016_scratch"], "5": ["4397_hug", "5875_escape", "6016_scratch"], "6": ["6035_capture", "5843_huddle with", "6017_encircle"], "7": ["1012_push", "6012_kiss", "5843_huddle with"], "8": ["6012_kiss", "5914_tickle", "6079_bother"], "9": ["5991_examine", "6004_herd", "5809_pull"], "10": ["5870_poke", "6035_capture", "6079_bother"], "11": ["5987_creep up on", "5787_accompany", "5814_talk"], "12": ["6035_capture", "5914_tickle", "5809_pull"], "13": ["5948_flirt with", "6079_bother", "5987_creep up on"], "14": ["1145_leave", "6005_throw", "6017_encircle"], "15": ["5948_flirt with", "5816_ignore", "5986_fight"], "16": ["5849_approach", "4408_lead", "6004_herd"], "17": ["1145_leave", "5914_tickle", "6012_kiss"], "18": ["6079_bother", "5870_poke", "5986_fight"], "19": ["5914_tickle", "6004_herd", "5843_huddle with"], "20": ["5914_tickle", "5875_escape", "6005_throw"], "21": ["5986_fight", "6017_encircle", "4408_lead"], "22": ["5948_flirt with", "5814_talk", "6035_capture"], "23": ["5987_creep up on", "5870_poke", "5849_approach"], "24": ["4397_hug", "5991_examine", "6004_herd"], "25": ["6017_encircle", "1012_push", "6079_bother"], "26": ["5849_approach", "5948_flirt with", "5870_poke"], "27": ["4408_lead", "5902_hit", "5787_accompany"], "28": ["5991_examine", "5948_flirt with", "5986_fight"], "29": ["5878_follow", "6012_kiss", "6004_herd"], "30": ["5843_huddle with", "1012_push", "5987_creep up on"], "31": ["5948_flirt with", "5914_tickle", "6035_capture"], "32": ["5816_ignore", "6079_bother", "5986_fight"], "33": ["5986_fight", "6012_kiss", "5914_tickle"], "34": ["6079_bother", "5816_ignore", "4408_lead"], "35": ["5849_approach", "5987_creep up on", "4397_hug"], "36": ["6079_bother", "6005_throw", "6017_encircle"], "37": ["1145_leave", "6004_herd", "5987_creep up on"], "38": ["5849_approach", "5843_huddle with", "5875_escape"], "39": ["5991_examine", "5875_escape", "4408_lead"], "40": ["6079_bother", "5816_ignore", "6016_scratch"], "41": ["5878_follow", "6034_avoid", "5870_poke"], "42": ["5878_follow", "6012_kiss", "6005_throw"], "43": ["6017_encircle", "5849_approach", "5991_examine"], "44": ["6016_scratch", "6017_encircle", "5987_creep up on"]}