{"0": ["5914_tickle", "5875_escape", "6079_bother"], "1": ["4397_hug", "5787_accompany", "5878_follow"], "2": ["5816_ignore", "5843_huddle with", "5814_talk"], "3": ["5986_fight", "6079_bother", "5902_hit"], "4": ["5914_tickle", "1145_leave", "6016_scratch"], "5": ["6016_scratch", "6079_bother", "5814_talk"], "6": ["5948_flirt with", "6017_encircle", "5987_creep up on"], "7": ["5814_talk", "6035_capture", "5902_hit"], "8": ["5914_tickle", "5843_huddle with", "5875_escape"], "9": ["6005_throw", "1145_leave", "5914_tickle"], "10": ["6017_encircle", "5816_ignore", "6012_kiss"], "11": ["5843_huddle with", "5816_ignore", "6004_herd"], "12": ["6034_avoid", "5914_tickle", "4408_lead"], "13": ["5814_talk", "5849_approach", "5914_tickle"], "14": ["1145_leave", "4397_hug", "5948_flirt with"], "15": ["5875_escape", "5902_hit", "5986_fight"], "16": ["5843_huddle with", "1012_push", "5878_follow"], "17": ["6005_throw", "5902_hit", "4397_hug"], "18": ["5991_examine", "5843_huddle with", "6017_encircle"], "19": ["5870_poke", "6017_encircle", "6035_capture"], "20": ["5948_flirt with", "6005_throw", "6017_encircle"], "21": ["5948_flirt with", "5878_follow", "5849_approach"], "22": ["5987_creep up on", "5849_approach", "5843_huddle with"], "23": ["5914_tickle", "5849_approach", "5816_ignore"], "24": ["5816_ignore", "6035_capture", "6004_herd"], "25": ["5816_ignore", "6079_bother", "5843_huddle with"], "26": ["4397_hug", "5914_tickle", "5849_approach"], "27": ["5987_creep up on", "5787_accompany", "6017_encircle"], "28": ["1145_leave", "6005_throw", "5986_fight"], "29": ["5878_follow", "5809_pull", "5843_huddle with"], "30": ["5787_accompany", "5902_hit", "4397_hug"], "31": ["6005_throw", "6012_kiss", "5986_fight"], "32": ["5870_poke", "1012_push", "5809_pull"], "33": ["5902_hit", "5809_pull", "6017_encircle"], "34": ["5902_hit", "6005_throw", "5878_follow"], "35": ["6079_bother", "6016_scratch", "5849_approach"], "36": ["6016_scratch", "5843_huddle with", "6034_avoid"], "37": ["6016_scratch", "5870_poke", "5991_examine"], "38": ["6016_scratch", "5902_hit", "5986_fight"], "39": ["6017_encircle", "5875_escape", "6004_herd"], "40": ["6004_herd", "6016_scratch", "6017_encircle"], "41": ["5902_hit", "6016_scratch", "6005_throw"], "42": ["4408_lead", "5902_hit", "1145_leave"], "43": ["4397_hug", "5816_ignore", "1012_push"], "44": ["5787_accompany", "5875_escape", "5902_hit"]}